agentrpc/__init__.py
agentrpc/client.py
agentrpc/errors.py
agentrpc/http_client.py
agentrpc/openai.py
agentrpc-0.0.8.dist-info/METADATA
agentrpc-0.0.8.dist-info/WHEEL
agentrpc-0.0.8.dist-info/top_level.txt
agentrpc-0.0.8.dist-info/RECORD
