Metadata-Version: 2.2
Name: agentrpc
Version: 0.0.8
Summary: Python SDK for AgentRPC
License: Apache-2.0
Project-URL: Homepage, https://agentrpc.com
Classifier: Programming Language :: Python :: 3
Classifier: Operating System :: OS Independent
Requires-Python: >=3.9
Requires-Dist: requests>=2.31.0
Requires-Dist: openai>=1.12.0
Requires-Dist: build>=1.2.2.post1
Requires-Dist: openai-agents>=0.0.4
Provides-Extra: dev
Requires-Dist: ruff>=0.3.0; extra == "dev"
Requires-Dist: pytest>=7.0.0; extra == "dev"
Requires-Dist: python-dotenv>=1.0.0; extra == "dev"
Requires-Dist: build>=1.0.3; extra == "dev"
Requires-Dist: twine>=4.0.0; extra == "dev"
